jsr_fun/__init__.py
jsr_fun/bin/a.json
jsr_fun/bin/campp.py
jsr_fun/bin/campp1.py
jsr_fun/bin/split.py
jsr_fun/bin/test-ct.py
jsr_fun/bin/test-file1.py
jsr_fun/bin/test-srt.py
jsr_fun/bin/test-streaming.py
jsr_fun/bin/test-vad.py
jsr_fun/paraformer-zh-spk/README_zh.md
jsr_fun/paraformer-zh-spk/__init__.py
jsr_fun/paraformer-zh-spk/demo.py
jsr_fun/paraformer-zh-spk/demo.sh
jsr_fun-0.1.0.dist-info/METADATA
jsr_fun-0.1.0.dist-info/WHEEL
jsr_fun-0.1.0.dist-info/RECORD
