Metadata-Version: 2.1
Name: jsr-fun
Version: 0.1.0
Summary: 
Author: dayn9t
Author-email: dayn9t@gmail.com
Requires-Python: >=3.12,<4.0
Classifier: Programming Language :: Python :: 3
Classifier: Programming Language :: Python :: 3.12
Classifier: Programming Language :: Python :: 3.13
Requires-Dist: addict
Requires-Dist: datasets
Requires-Dist: funasr
Requires-Dist: jcx
Requires-Dist: llvmlite
Requires-Dist: loguru
Requires-Dist: pydantic
Requires-Dist: pydub
Requires-Dist: rustshed
Requires-Dist: torch
Requires-Dist: torchaudio
